Module-Library/SPI_slave/top/top.sv
module top (
    input  logic [9:0] SW,
    input  logic [1:0] KEY,
    input  logic       CLOCK_50,

    output logic [6:0] HEX5,
    output logic [6:0] HEX4,
    output logic [6:0] HEX3,
    output logic [6:0] HEX2,
    output logic [6:0] HEX1,
    output logic [6:0] HEX0,
    output logic [9:0] LEDR,

    output logic [3:0] VGA_R,
    output logic [3:0] VGA_G,
    output logic [3:0] VGA_B,
    output logic       VGA_HS,
    output logic       VGA_VS,

    inout  logic [15:0] ARDUINO_IO
);

    localparam MEM_WIDTH = 8;

    logic clk, rst;
    logic sclk, cs_n, mosi, miso;
    logic d_valid;
    logic [MEM_WIDTH-1:0] dout;

    assign clk  = CLOCK_50;
    assign rst  = ~KEY[0];

    // Physical pins
    assign sclk          = ARDUINO_IO[0];
    assign mosi          = ARDUINO_IO[1];
    assign ARDUINO_IO[2] = miso;
    assign cs_n          = ~SW[0] & ARDUINO_IO[3];

    // Debug: show last received byte on LEDs
    assign LEDR = {sclk, mosi, dout};

    // Unused outputs
    assign HEX5 = '1; assign HEX4 = '1; assign HEX3 = '1;
    assign HEX2 = '1; assign HEX1 = '1; assign HEX0 = '1;
    assign VGA_R = '0; assign VGA_G = '0; assign VGA_B = '0;
    assign VGA_HS = '1; assign VGA_VS = '1;

    spi_slave #(.WIDTH(MEM_WIDTH)) SPI (
        .clk(clk),
        .rst(rst),
        .sclk(sclk),
        .cs_n(cs_n),
        .mosi(mosi),
        .miso(miso),
        .din('0),
        .d_valid(d_valid),
        .dout(dout)
    );

endmodule

module spi_slave #(
    parameter WIDTH = 8
) (
    input  logic             clk,      // system clock (50 MHz)
    input  logic             rst,      // active high reset

    // SPI wires
    input  logic             sclk,     // SPI clock (up to 45 MHz)
    input  logic             cs_n,     // chip select (active low)
    input  logic             mosi,     // master out slave in
    output logic             miso,     // master in slave out

    // Data wires
    input  logic [WIDTH-1:0] din,      // data to send to master
    output logic             d_valid,  // pulse in sys clk domain when new data received
    output logic [WIDTH-1:0] dout      // received data (stable in sys clk domain)
);

    //==========================================================================
    // SPI Clock Domain - Shift In (MOSI)
    //==========================================================================
    logic [WIDTH-1:0]       shift_in;
    logic [$clog2(WIDTH):0] bit_count;
    logic [WIDTH-1:0]       captured_data;
    logic                   data_ready_toggle;

    always_ff @(posedge sclk or posedge rst or posedge cs_n) begin
        if (rst || cs_n) begin
            shift_in          <= '0;
            bit_count         <= '0;
            data_ready_toggle <= '0;
            captured_data     <= '0;
        end else begin
            shift_in <= {shift_in[WIDTH-2:0], mosi};
            
            if (bit_count == WIDTH - 1) begin
                captured_data     <= {shift_in[WIDTH-2:0], mosi};
                data_ready_toggle <= ~data_ready_toggle;
                bit_count         <= '0;
            end else begin
                bit_count <= bit_count + 1;
            end
        end
    end

    //==========================================================================
    // SPI Clock Domain - Shift Out (MISO) on falling edge
    //==========================================================================
    logic [WIDTH-1:0] shift_out;
    logic             cs_n_prev;
    
    always_ff @(negedge sclk or posedge rst) begin
        if (rst) begin
            shift_out <= '0;
            cs_n_prev <= 1'b1;
        end else begin
            cs_n_prev <= cs_n;
            
            // Detect falling edge of cs_n (start of transaction)
            if (!cs_n && cs_n_prev) begin
                // Load new data at start of transaction
                shift_out <= din;
            end else if (!cs_n) begin
                // Shift out during transaction
                shift_out <= {shift_out[WIDTH-2:0], 1'b0};
            end
        end
    end

    assign miso = shift_out[WIDTH-1];

    //==========================================================================
    // Clock Domain Crossing - Toggle Synchronizer
    //==========================================================================
    logic toggle_sync1, toggle_sync2, toggle_sync3;

    always_ff @(posedge clk or posedge rst) begin
        if (rst) begin
            toggle_sync1 <= '0;
            toggle_sync2 <= '0;
            toggle_sync3 <= '0;
        end else begin
            toggle_sync1 <= data_ready_toggle;
            toggle_sync2 <= toggle_sync1;
            toggle_sync3 <= toggle_sync2;
        end
    end

    //==========================================================================
    // Clock Domain Crossing - Data Synchronization
    //==========================================================================
    logic [WIDTH-1:0] captured_sync1, captured_sync2;
    
    always_ff @(posedge clk or posedge rst) begin
        if (rst) begin
            captured_sync1 <= '0;
            captured_sync2 <= '0;
        end else begin
            captured_sync1 <= captured_data;
            captured_sync2 <= captured_sync1;
        end
    end

    //==========================================================================
    // System Clock Domain - Edge Detection and Output
    //==========================================================================
    always_ff @(posedge clk or posedge rst) begin
        if (rst) begin
            dout    <= '0;
            d_valid <= 1'b0;
        end else begin
            if (toggle_sync2 ^ toggle_sync3) begin
                // New data available
                dout    <= captured_sync2;
                d_valid <= 1'b1;
            end else begin
                d_valid <= 1'b0;
            end
        end
    end

endmodule

Module-Library/SPI_slave/testbench/tb_spi_slave.sv
`timescale 1ns/1ps

module tb_spi_slave;

    parameter WIDTH = 8;

    localparam real CLK_T  = 20.0;
    localparam real SCLK_T = 1000.0;

    logic clk;
    logic rst;
    logic sclk;
    logic cs_n;
    logic mosi;
    logic miso;

    logic [WIDTH-1:0] din;
    logic             d_valid;
    logic [WIDTH-1:0] dout;

    spi_slave #(.WIDTH(WIDTH)) dut (
        .clk(clk),
        .rst(rst),
        .sclk(sclk),
        .cs_n(cs_n),
        .mosi(mosi),
        .miso(miso),
        .din(din),
        .d_valid(d_valid),
        .dout(dout)
    );

    initial clk = 0;
    always #(CLK_T / 2.0) clk = ~clk;

    task automatic spi_send_byte(input [7:0] data);
        for (int i = 7; i >= 0; i--) begin
            mosi = data[i];        // set MOSI
            #(SCLK_T / 2.0);
            sclk = 1;              // rising: slave samples
            #(SCLK_T / 2.0);
            sclk = 0;              // falling: ready for next bit
        end
    endtask

    always @(posedge clk) begin
        if (d_valid)
            $display("[%0t] d_valid pulse — dout = 0x%02h", $time, dout);
    end

    initial begin
        $dumpfile("tb_spi_slave.vcd");
        $dumpvars(0, tb_spi_slave);

        rst  = 1;
        cs_n = 1;
        mosi = 0;
        sclk = 0;
        din  = 8'hA5;

        repeat (5) @(posedge clk);
        rst = 0;
        repeat (2) @(posedge clk);

        // --- Transaction 1 ---
        cs_n = 0;
        spi_send_byte(8'h3C);
        spi_send_byte(8'h80);
        cs_n = 1;

        repeat (10) @(posedge clk);

        // --- Transaction 2 ---
        cs_n = 0;
        spi_send_byte(8'h36);
        spi_send_byte(8'h1B);
        cs_n = 1;

        repeat (10) @(posedge clk);

        $display("[%0t] Final dout = 0x%02h", $time, dout);
        $finish;
    end

endmodule

Module-Library/SPI_slave/sim/tb_spi_slave.vcd
$version Generated by VerilatedVcd $end
$timescale 1ps $end
 $scope module TOP $end
  $scope module tb_spi_slave $end
   $var wire 32 7 WIDTH [31:0] $end
   $var real 64 8 CLK_T $end
   $var real 64 : SCLK_T $end
   $var wire 1 6 clk $end
   $var wire 1 # rst $end
   $var wire 1 $ sclk $end
   $var wire 1 % cs_n $end
   $var wire 1 & mosi $end
   $var wire 1 ( miso $end
   $var wire 8 ' din [7:0] $end
   $var wire 1 + d_valid $end
   $var wire 8 , dout [7:0] $end
   $scope module dut $end
    $var wire 32 7 WIDTH [31:0] $end
    $var wire 1 6 clk $end
    $var wire 1 # rst $end
    $var wire 1 $ sclk $end
    $var wire 1 % cs_n $end
    $var wire 1 & mosi $end
    $var wire 1 ( miso $end
    $var wire 8 ' din [7:0] $end
    $var wire 1 + d_valid $end
    $var wire 8 , dout [7:0] $end
    $var wire 8 2 shift_in [7:0] $end
    $var wire 4 3 bit_count [3:0] $end
    $var wire 8 4 captured_data [7:0] $end
    $var wire 1 5 data_ready_toggle $end
    $var wire 8 ) shift_out [7:0] $end
    $var wire 1 * cs_n_prev $end
    $var wire 1 - toggle_sync1 $end
    $var wire 1 . toggle_sync2 $end
    $var wire 1 / toggle_sync3 $end
    $var wire 8 0 captured_sync1 [7:0] $end
    $var wire 8 1 captured_sync2 [7:0] $end
   $upscope $end
  $upscope $end
 $upscope $end
$enddefinitions $end


#0
1#
0$
1%
0&
b10100101 '
0(
b00000000 )
0*
0+
b00000000 ,
0-
0.
0/
b00000000 0
b00000000 1
b00000000 2
b0000 3
b00000000 4
05
06
b00000000000000000000000000001000 7
r20 8
r1000 :
#10000
16
#20000
06
#30000
16
#40000
06
#50000
16
#60000
06
#70000
16
#80000
06
#90000
0#
16
#100000
06
#110000
16
#120000
06
#130000
0%
16
#140000
06
#150000
16
#160000
06
#170000
16
#180000
06
#190000
16
#200000
06
#210000
16
#220000
06
#230000
16
#240000
06
#250000
16
#260000
06
#270000
16
#280000
06
#290000
16
#300000
06
#310000
16
#320000
06
#330000
16
#340000
06
#350000
16
#360000
06
#370000
16
#380000
06
#390000
16
#400000
06
#410000
16
#420000
06
#430000
16
#440000
06
#450000
16
#460000
06
#470000
16
#480000
06
#490000
16
#500000
06
#510000
16
#520000
06
#530000
16
#540000
06
#550000
16
#560000
06
#570000
16
#580000
06
#590000
16
#600000
06
#610000
16
#620000
06
#630000
1$
b0001 3
16
#640000
06
#650000
16
#660000
06
#670000
16
#680000
06
#690000
16
#700000
06
#710000
16
#720000
06
#730000
16
#740000
06
#750000
16
#760000
06
#770000
16
#780000
06
#790000
16
#800000
06
#810000
16
#820000
06
#830000
16
#840000
06
#850000
16
#860000
06
#870000
16
#880000
06
#890000
16
#900000
06
#910000
16
#920000
06
#930000
16
#940000
06
#950000
16
#960000
06
#970000
16
#980000
06
#990000
16
#1000000
06
#1010000
16
#1020000
06
#1030000
16
#1040000
06
#1050000
16
#1060000
06
#1070000
16
#1080000
06
#1090000
16
#1100000
06
#1110000
16
#1120000
06
#1130000
0$
16
#1140000
06
#1150000
16
#1160000
06
#1170000
16
#1180000
06
#1190000
16
#1200000
06
#1210000
16
#1220000
06
#1230000
16
#1240000
06
#1250000
16
#1260000
06
#1270000
16
#1280000
06
#1290000
16
#1300000
06
#1310000
16
#1320000
06
#1330000
16
#1340000
06
#1350000
16
#1360000
06
#1370000
16
#1380000
06
#1390000
16
#1400000
06
#1410000
16
#1420000
06
#1430000
16
#1440000
06
#1450000
16
#1460000
06
#1470000
16
#1480000
06
#1490000
16
#1500000
06
#1510000
16
#1520000
06
#1530000
16
#1540000
06
#1550000
16
#1560000
06
#1570000
16
#1580000
06
#1590000
16
#1600000
06
#1610000
16
#1620000
06
#1630000
1$
b0010 3
16
#1640000
06
#1650000
16
#1660000
06
#1670000
16
#1680000
06
#1690000
16
#1700000
06
#1710000
16
#1720000
06
#1730000
16
#1740000
06
#1750000
16
#1760000
06
#1770000
16
#1780000
06
#1790000
16
#1800000
06
#1810000
16
#1820000
06
#1830000
16
#1840000
06
#1850000
16
#1860000
06
#1870000
16
#1880000
06
#1890000
16
#1900000
06
#1910000
16
#1920000
06
#1930000
16
#1940000
06
#1950000
16
#1960000
06
#1970000
16
#1980000
06
#1990000
16
#2000000
06
#2010000
16
#2020000
06
#2030000
16
#2040000
06
#2050000
16
#2060000
06
#2070000
16
#2080000
06
#2090000
16
#2100000
06
#2110000
16
#2120000
06
#2130000
0$
1&
16
#2140000
06
#2150000
16
#2160000
06
#2170000
16
#2180000
06
#2190000
16
#2200000
06
#2210000
16
#2220000
06
#2230000
16
#2240000
06
#2250000
16
#2260000
06
#2270000
16
#2280000
06
#2290000
16
#2300000
06
#2310000
16
#2320000
06
#2330000
16
#2340000
06
#2350000
16
#2360000
06
#2370000
16
#2380000
06
#2390000
16
#2400000
06
#2410000
16
#2420000
06
#2430000
16
#2440000
06
#2450000
16
#2460000
06
#2470000
16
#2480000
06
#2490000
16
#2500000
06
#2510000
16
#2520000
06
#2530000
16
#2540000
06
#2550000
16
#2560000
06
#2570000
16
#2580000
06
#2590000
16
#2600000
06
#2610000
16
#2620000
06
#2630000
1$
b00000001 2
b0011 3
16
#2640000
06
#2650000
16
#2660000
06
#2670000
16
#2680000
06
#2690000
16
#2700000
06
#2710000
16
#2720000
06
#2730000
16
#2740000
06
#2750000
16
#2760000
06
#2770000
16
#2780000
06
#2790000
16
#2800000
06
#2810000
16
#2820000
06
#2830000
16
#2840000
06
#2850000
16
#2860000
06
#2870000
16
#2880000
06
#2890000
16
#2900000
06
#2910000
16
#2920000
06
#2930000
16
#2940000
06
#2950000
16
#2960000
06
#2970000
16
#2980000
06
#2990000
16
#3000000
06
#3010000
16
#3020000
06
#3030000
16
#3040000
06
#3050000
16
#3060000
06
#3070000
16
#3080000
06
#3090000
16
#3100000
06
#3110000
16
#3120000
06
#3130000
0$
16
#3140000
06
#3150000
16
#3160000
06
#3170000
16
#3180000
06
#3190000
16
#3200000
06
#3210000
16
#3220000
06
#3230000
16
#3240000
06
#3250000
16
#3260000
06
#3270000
16
#3280000
06
#3290000
16
#3300000
06
#3310000
16
#3320000
06
#3330000
16
#3340000
06
#3350000
16
#3360000
06
#3370000
16
#3380000
06
#3390000
16
#3400000
06
#3410000
16
#3420000
06
#3430000
16
#3440000
06
#3450000
16
#3460000
06
#3470000
16
#3480000
06
#3490000
16
#3500000
06
#3510000
16
#3520000
06
#3530000
16
#3540000
06
#3550000
16
#3560000
06
#3570000
16
#3580000
06
#3590000
16
#3600000
06
#3610000
16
#3620000
06
#3630000
1$
b00000011 2
b0100 3
16
