Module-Library/SPI_slave/core/spi_slave.sv
module spi_slave #(
    parameter WIDTH = 8
) (
    input  logic             clk,      // system clock (added)
    input  logic             rst,

    // SPI wires
    input  logic             sclk,
    input  logic             cs_n,
    input  logic             mosi,
    output logic             miso,

    // Data wires
    input  logic [WIDTH-1:0] din,
    output logic             d_valid,  // pulse in sys clk domain
    output logic [WIDTH-1:0] dout      // stable in sys clk domain
);

    // SPI domain 
    logic [WIDTH-1:0]       shift_in;
    logic [$clog2(WIDTH):0] count;
    logic [WIDTH-1:0]       captured;
    logic                   toggle;

    always_ff @(posedge sclk or posedge rst or posedge cs_n) begin
        if (rst || cs_n) begin
            shift_in <= '0;
            count    <= '0;
            toggle   <= '0;
            captured <= '0;
        end else begin
            shift_in <= {shift_in[WIDTH-2:0], mosi};
            if (count == WIDTH - 1) begin
                captured <= {shift_in[WIDTH-2:0], mosi};  // latch stable data
                toggle   <= ~toggle;                       // signal new data
                count    <= '0;
            end else begin
                count <= count + 1;
            end
        end
    end

    // MISO (shift out on falling edge) 
    logic [WIDTH-1:0] shift_out;

    always_ff @(negedge sclk or posedge rst) begin
        if (rst)       shift_out <= '0;
        else if (!cs_n) shift_out <= {shift_out[WIDTH-2:0], 1'b0};
        else            shift_out <= din;
    end

    assign miso = shift_out[WIDTH-1];

    // CDC: toggle sync into sys clk domain 
    logic sync1, sync2, sync3;

    always_ff @(posedge clk) begin
        sync1 <= toggle;
        sync2 <= sync1;
        sync3 <= sync2;
    end

    // Edge detect -> d_valid pulse, latch data at same time
    always_ff @(posedge clk) begin
        if (sync2 ^ sync3) begin
            dout    <= captured;
            d_valid <= 1'b1;
        end else begin
            d_valid <= 1'b0;
        end
    end

endmodule

Module-Library/SPI_slave/testbench/tb_spi_slave.sv
`timescale 1ns/1ps

module tb_spi_slave;

    parameter WIDTH = 8;

    localparam real CLK_T  = 20.0;
    localparam real SCLK_T = 1000.0;

    logic clk;
    logic rst;
    logic sclk;
    logic cs_n;
    logic mosi;
    logic miso;

    logic [WIDTH-1:0] din;
    logic             d_valid;
    logic [WIDTH-1:0] dout;

    spi_slave #(.WIDTH(WIDTH)) dut (
        .clk(clk),
        .rst(rst),
        .sclk(sclk),
        .cs_n(cs_n),
        .mosi(mosi),
        .miso(miso),
        .din(din),
        .d_valid(d_valid),
        .dout(dout)
    );

    initial clk = 0;
    always #(CLK_T / 2.0) clk = ~clk;

    task automatic spi_send_byte(input [7:0] data);
        for (int i = 7; i >= 0; i--) begin
            mosi = data[i];        // set MOSI
            #(SCLK_T / 2.0);
            sclk = 1;              // rising: slave samples
            #(SCLK_T / 2.0);
            sclk = 0;              // falling: ready for next bit
        end
    endtask

    always @(posedge clk) begin
        if (d_valid)
            $display("[%0t] d_valid pulse — dout = 0x%02h", $time, dout);
    end

    initial begin
        $dumpfile("tb_spi_slave.vcd");
        $dumpvars(0, tb_spi_slave);

        rst  = 1;
        cs_n = 1;
        mosi = 0;
        sclk = 0;
        din  = 8'hA5;

        repeat (5) @(posedge clk);
        rst = 0;
        repeat (2) @(posedge clk);

        // --- Transaction 1 ---
        cs_n = 0;
        spi_send_byte(8'h3C);
        spi_send_byte(8'h80);
        cs_n = 1;

        repeat (10) @(posedge clk);

        // --- Transaction 2 ---
        cs_n = 0;
        spi_send_byte(8'h36);
        spi_send_byte(8'h1B);
        cs_n = 1;

        repeat (10) @(posedge clk);

        $display("[%0t] Final dout = 0x%02h", $time, dout);
        $finish;
    end

endmodule

Module-Library/SPI_slave/sim/tb_spi_slave.vcd
$version Generated by VerilatedVcd $end
$timescale 1ps $end
 $scope module TOP $end
  $scope module tb_spi_slave $end
   $var wire 32 4 WIDTH [31:0] $end
   $var real 64 5 CLK_T $end
   $var real 64 7 SCLK_T $end
   $var wire 1 1 clk $end
   $var wire 1 # rst $end
   $var wire 1 $ sclk $end
   $var wire 1 % cs_n $end
   $var wire 1 & mosi $end
   $var wire 1 2 miso $end
   $var wire 8 ' din [7:0] $end
   $var wire 1 ( d_valid $end
   $var wire 8 ) dout [7:0] $end
   $scope module dut $end
    $var wire 32 4 WIDTH [31:0] $end
    $var wire 1 1 clk $end
    $var wire 1 # rst $end
    $var wire 1 $ sclk $end
    $var wire 1 % cs_n $end
    $var wire 1 & mosi $end
    $var wire 1 2 miso $end
    $var wire 8 ' din [7:0] $end
    $var wire 1 ( d_valid $end
    $var wire 8 ) dout [7:0] $end
    $var wire 8 - shift_in [7:0] $end
    $var wire 4 . count [3:0] $end
    $var wire 8 / captured [7:0] $end
    $var wire 1 0 toggle $end
    $var wire 8 3 shift_out [7:0] $end
    $var wire 1 * sync1 $end
    $var wire 1 + sync2 $end
    $var wire 1 , sync3 $end
   $upscope $end
  $upscope $end
 $upscope $end
$enddefinitions $end


#0
1#
0$
1%
0&
b10100101 '
0(
b00000000 )
0*
0+
0,
b00000000 -
b0000 .
b00000000 /
00
01
02
b00000000 3
b00000000000000000000000000001000 4
r20 5
r1000 7
#10000
11
#20000
01
#30000
11
#40000
01
#50000
11
#60000
01
#70000
11
#80000
01
#90000
0#
11
#100000
01
#110000
11
#120000
01
#130000
0%
11
#140000
01
#150000
11
#160000
01
#170000
11
#180000
01
#190000
11
#200000
01
#210000
11
#220000
01
#230000
11
#240000
01
#250000
11
#260000
01
#270000
11
#280000
01
#290000
11
#300000
01
#310000
11
#320000
01
#330000
11
#340000
01
#350000
11
#360000
01
#370000
11
#380000
01
#390000
11
#400000
01
#410000
11
#420000
01
#430000
11
#440000
01
#450000
11
#460000
01
#470000
11
#480000
01
#490000
11
#500000
01
#510000
11
#520000
01
#530000
11
#540000
01
#550000
11
#560000
01
#570000
11
#580000
01
#590000
11
#600000
01
#610000
11
#620000
01
#630000
1$
b0001 .
11
#640000
01
#650000
11
#660000
01
#670000
11
#680000
01
#690000
11
#700000
01
#710000
11
#720000
01
#730000
11
#740000
01
#750000
11
#760000
01
#770000
11
#780000
01
#790000
11
#800000
01
#810000
11
#820000
01
#830000
11
#840000
01
#850000
11
#860000
01
#870000
11
#880000
01
#890000
11
#900000
01
#910000
11
#920000
01
#930000
11
#940000
01
#950000
11
#960000
01
#970000
11
#980000
01
#990000
11
#1000000
01
#1010000
11
#1020000
01
#1030000
11
#1040000
01
#1050000
11
#1060000
01
#1070000
11
#1080000
01
#1090000
11
#1100000
01
#1110000
11
#1120000
01
#1130000
0$
11
#1140000
01
#1150000
11
#1160000
01
#1170000
11
#1180000
01
#1190000
11
#1200000
01
#1210000
11
#1220000
01
#1230000
11
#1240000
01
#1250000
11
#1260000
01
#1270000
11
#1280000
01
#1290000
11
#1300000
01
#1310000
11
#1320000
01
#1330000
11
#1340000
01
#1350000
11
#1360000
01
#1370000
11
#1380000
01
#1390000
11
#1400000
01
#1410000
11
#1420000
01
#1430000
11
#1440000
01
#1450000
11
#1460000
01
#1470000
11
#1480000
01
#1490000
11
#1500000
01
#1510000
11
#1520000
01
#1530000
11
#1540000
01
#1550000
11
#1560000
01
#1570000
11
#1580000
01
#1590000
11
#1600000
01
#1610000
11
#1620000
01
#1630000
1$
b0010 .
11
#1640000
01
#1650000
11
#1660000
01
#1670000
11
#1680000
01
#1690000
11
#1700000
01
#1710000
11
#1720000
01
#1730000
11
#1740000
01
#1750000
11
#1760000
01
#1770000
11
#1780000
01
#1790000
11
#1800000
01
#1810000
11
#1820000
01
#1830000
11
#1840000
01
#1850000
11
#1860000
01
#1870000
11
#1880000
01
#1890000
11
#1900000
01
#1910000
11
#1920000
01
#1930000
11
#1940000
01
#1950000
11
#1960000
01
#1970000
11
#1980000
01
#1990000
11
#2000000
01
#2010000
11
#2020000
01
#2030000
11
#2040000
01
#2050000
11
#2060000
01
#2070000
11
#2080000
01
#2090000
11
#2100000
01
#2110000
11
#2120000
01
#2130000
0$
1&
11
#2140000
01
#2150000
11
#2160000
01
#2170000
11
#2180000
01
#2190000
11
#2200000
01
#2210000
11
#2220000
01
#2230000
11
#2240000
01
#2250000
11
#2260000
01
#2270000
11
#2280000
01
#2290000
11
#2300000
01
#2310000
11
#2320000
01
#2330000
11
#2340000
01
#2350000
11
#2360000
01
#2370000
11
#2380000
01
#2390000
11
#2400000
01
#2410000
11
#2420000
01
#2430000
11
#2440000
01
#2450000
11
#2460000
01
#2470000
11
#2480000
01
#2490000
11
#2500000
01
#2510000
11
#2520000
01
#2530000
11
#2540000
01
#2550000
11
#2560000
01
#2570000
11
#2580000
01
#2590000
11
#2600000
01
#2610000
11
#2620000
01
#2630000
1$
b00000001 -
b0011 .
11
#2640000
01
#2650000
11
#2660000
01
#2670000
11
#2680000
01
#2690000
11
#2700000
01
#2710000
11
#2720000
01
#2730000
11
#2740000
01
#2750000
11
#2760000
01
#2770000
11
#2780000
01
#2790000
11
#2800000
01
#2810000
11
#2820000
01
#2830000
11
#2840000
01
#2850000
11
#2860000
01
#2870000
11
#2880000
01
#2890000
11
#2900000
01
#2910000
11
#2920000
01
#2930000
11
#2940000
01
#2950000
11
#2960000
01
#2970000
11
#2980000
01
#2990000
11
#3000000
01
#3010000
11
#3020000
01
#3030000
11
#3040000
01
#3050000
11
#3060000
01
#3070000
11
#3080000
01
#3090000
11
#3100000
01
#3110000
11
#3120000
01
#3130000
0$
11
#3140000
01
#3150000
11
#3160000
01
#3170000
11
#3180000
01
#3190000
11
#3200000
01
#3210000
11
#3220000
01
#3230000
11
#3240000
01
#3250000
11
#3260000
01
#3270000
11
#3280000
01
#3290000
11
#3300000
01
#3310000
11
#3320000
01
#3330000
11
#3340000
01
#3350000
11
#3360000
01
#3370000
11
#3380000
01
#3390000
11
#3400000
01
#3410000
11
#3420000
01
#3430000
11
#3440000
01
#3450000
11
#3460000
01
#3470000
11
#3480000
01
#3490000
11
#3500000
01
#3510000
11
#3520000
01
#3530000
11
#3540000
01
#3550000
11
#3560000
01
#3570000
11
#3580000
01
#3590000
11
#3600000
01
#3610000
11
#3620000
01
#3630000
1$
b00000011 -
b0100 .
11
