Quartus_Project/top.sv
module top (
	input  logic [9:0] SW,
	input  logic [1:0] KEY,
	input  logic       CLOCK_50,

	output logic [6:0] HEX5,
	output logic [6:0] HEX4,
	output logic [6:0] HEX3,
	output logic [6:0] HEX2,
	output logic [6:0] HEX1,
	output logic [6:0] HEX0,
	output logic [9:0] LEDR,

    output logic [3:0] VGA_R,
    output logic [3:0] VGA_G,
    output logic [3:0] VGA_B,
    output logic       VGA_HS,
    output logic       VGA_VS,

    inout  logic [15:0] ARDUINO_IO
);

	localparam
		RES_X = 320,
		RES_Y = 240,
		MEM_WIDTH = 8;

	// Helper wires
	logic 			clk;
	logic			rst;

	logic [3:0]		vga_r;
	logic [3:0]		vga_g;
	logic [3:0]		vga_b;
	logic			h_sync;
	logic			v_sync;

	logic			rx;
    logic [31:0]    addr_count;

	// Helper assignments
	assign clk = CLOCK_50;
	assign rst = ~KEY[0];

	// Assignments
	assign LEDR = addr_count[9:0];
	assign VGA_R = vga_r;
	assign VGA_G = vga_g;
	assign VGA_B = vga_b;
	assign VGA_HS = h_sync;
	assign VGA_VS = v_sync;
    assign rx     = ARDUINO_IO[0];

	// Module instantiation
	vga_uart #(
        .RES_X(RES_X),
        .RES_Y(RES_Y),
        .MEM_WIDTH(MEM_WIDTH)
    ) VGA_UART (
        .clk(clk),
        .rst(rst),
        .rx(rx),
        .tx(),
        .vga_r(vga_r),
        .vga_g(vga_g),
        .vga_b(vga_b),
        .h_sync(h_sync),
        .v_sync(v_sync),
        .addr_count(addr_count)
    );

endmodule

module vga_uart #(
    parameter RES_X = 320,
    parameter RES_Y = 240,
    parameter RES_DIV = 2,
    parameter MEM_WIDTH = 8,
    parameter MEM_DEPTH = RES_X * RES_Y,
    parameter ADDR_WIDTH = $clog2(MEM_DEPTH),
    parameter PIXEL_WIDTH = 4
) (
    // Default wires
    input  logic                    clk, 
    input  logic                    rst,

    // UART wires
    input  logic                    rx,
    output logic                    tx,

    // VGA wires
    output logic [PIXEL_WIDTH-1:0]  vga_r,
    output logic [PIXEL_WIDTH-1:0]  vga_g,
    output logic [PIXEL_WIDTH-1:0]  vga_b,
    output logic                    h_sync,
    output logic                    v_sync,

    // Debug memory wires
    output logic [ADDR_WIDTH-1:0]   addr_count
);

    // Local parameters
    localparam 
        CLK_DIV     = 2,
        H_COUNT_MAX = 800,
        V_COUNT_MAX = 525,
        H_BITS      = $clog2(H_COUNT_MAX),
        V_BITS      = $clog2(V_COUNT_MAX),
        CLK_PER_BIT = 50,
        CLK_BITS    = 8,
        DATA_WIDTH  = MEM_WIDTH,
        PARITY_BITS = 0,
        STOP_BITS   = 1;

    // Helper wires
    // Memory helper wires
    logic [ADDR_WIDTH-1:0]  mem_addr;
    logic [MEM_WIDTH-1:0]   din;
    logic                   wen;
    logic [MEM_WIDTH-1:0]   dout; // unused

    // UART helper wires
    logic                   rx_din;
    logic [MEM_WIDTH-1:0]   rx_dout;
    logic                   rx_done;

    // Helper assignments
    assign rx_din   = rx;
    assign mem_addr = addr_count;

    // Memory counter wires
    
    always_ff @(posedge clk) begin
        if (rst) begin
            addr_count <= 0;
            wen        <= 1'b0;
        end
        else begin
            wen        <= 1'b0;
            if (rx_done) begin
                if (rx_dout[7] == 1'b1) begin
                    addr_count  <= 0;
                    wen         <= 1'b0;
                end
                else begin
                    din         <= rx_dout;
                    wen         <= 1'b1;
                    if (addr_count >= MEM_DEPTH - 1) begin
                        addr_count  <= 0;
                    end
                    else begin
                        addr_count  <= addr_count + 1;
                    end
                end
            end
        end
    end

    // Module instantiation
	vga_mem #(
        .RES_X(RES_X),
        .RES_Y(RES_Y),
        .MEM_WIDTH(MEM_WIDTH)
    ) VGA (
        .clk(clk),
        .rst(rst),
        .mem_addr(mem_addr),
        .din(din),
        .wen(wen),
        .dout(dout),
        .vga_r(vga_r),
        .vga_g(vga_g),
        .vga_b(vga_b),
        .h_sync(h_sync),
        .v_sync(v_sync)
    );

    uart_wrapper #(
        .CLK_BITS(CLK_BITS),
        .DATA_WIDTH(DATA_WIDTH),
        .PARITY_BITS(PARITY_BITS),
        .STOP_BITS(STOP_BITS)
    ) UART (
        .clk(clk),
        .rst(rst),
        .clk_per_bit(CLK_PER_BIT),

        .TX_dataIn(),
        .TX_en(),

        .TX_out(),
        .TX_done(),
        .TX_busy(),

        .RX_dataIn(rx_din),

        .RX_dataOut(rx_dout),
        .RX_done(rx_done),
        .RX_parityError()
    );
    
endmodule

module vga_mem #(
    parameter RES_X = 320,
    parameter RES_Y = 240,
    parameter RES_DIV = 2,
    parameter MEM_WIDTH = 8,
    parameter MEM_DEPTH = RES_X * RES_Y,
    parameter ADDR_WIDTH = $clog2(MEM_DEPTH),
    parameter PIXEL_WIDTH = 4
) (
    // Default wires
    input  logic                    clk, 
    input  logic                    rst,

    // Memory wires
    input  logic [ADDR_WIDTH-1:0]   mem_addr,
    input  logic [MEM_WIDTH-1:0]    din,
    input  logic                    wen,
    output logic [MEM_WIDTH-1:0]    dout, // unused

    // VGA wires
    output logic [PIXEL_WIDTH-1:0]  vga_r,
    output logic [PIXEL_WIDTH-1:0]  vga_g,
    output logic [PIXEL_WIDTH-1:0]  vga_b,
    output logic                    h_sync,
    output logic                    v_sync
);

    // Local parameters
    localparam 
        CLK_DIV     = 2,
        H_COUNT_MAX = 800,
        V_COUNT_MAX = 525,
        H_BITS      = $clog2(H_COUNT_MAX),
        V_BITS      = $clog2(V_COUNT_MAX);

    // VGA helper wires
    logic [$clog2(RES_X)-1:0]   mem_x;
    logic [$clog2(RES_Y)-1:0]   mem_y;
    logic [H_BITS-1:0]          vga_x;
    logic [V_BITS-1:0]          vga_y;
    logic                       vga_active;

    // Memory helper wires
    // Port A
    logic                       we_a;
    logic [ADDR_WIDTH-1:0]      addr_a;
    logic [MEM_WIDTH-1:0]       din_a;
    logic [MEM_WIDTH-1:0]       dout_a;

    // Port B
    // logic                       we_b;
    logic [ADDR_WIDTH-1:0]      addr_b;
    // logic [MEM_WIDTH-1:0]      din_b;
    logic [MEM_WIDTH-1:0]       dout_b;

    // Internal wires
    logic [ADDR_WIDTH-1:0]      mem_addr_vga;
    logic [MEM_WIDTH-1:0]       mem_d_out_vga;    

    // Wire assignment
    // Memory inputs
    assign addr_a   = mem_addr;
    assign din_a    = din;
    assign we_a     = wen;
    // Memory output
    assign dout     = dout_a;

    // VGA output
    // Using 0b00RRGGBB format
    assign vga_r    = vga_active ? {dout_b[5:4], 2'b00} : 4'b0000;
    assign vga_g    = vga_active ? {dout_b[3:2], 2'b00} : 4'b0000;
    assign vga_b    = vga_active ? {dout_b[1:0], 2'b00} : 4'b0000;

    // VGA memory assignments
    // Assuming smart synthesizer
    assign mem_x    = vga_x / RES_DIV; 
    assign mem_y    = vga_y / RES_DIV;
    assign addr_b   = mem_x + mem_y * RES_X;

    // // Assuming dumb synthesizer
    // assign mem_x    = vga_x >> 1;
    // assign mem_y    = vga_y >> 1;
    // assign addr_b   = mem_x + (vga_y << 6) + (vga_x << 8);   

    // Module instantiation
    vga #(
        .PIXEL_BITS(PIXEL_WIDTH),
        .CLK_DIV(CLK_DIV),
        .H_COUNT_MAX(H_COUNT_MAX),
        .V_COUNT_MAX(V_COUNT_MAX)
    ) VGA (
        .clk(clk),
        .rst(rst),
        .vga_r(),
        .vga_g(),
        .vga_b(),
        .h_sync(h_sync),
        .v_sync(v_sync),
        .vga_x(vga_x),
        .vga_y(vga_y),
        .vga_active(vga_active)
    );

    dp_ram_sync_read #(
        .DATA_WIDTH(MEM_WIDTH),
        .MEM_DEPTH(MEM_DEPTH)
    ) RAM (
        .clk(clk),
        .we_a(we_a),
        .addr_a(addr_a),
        .din_a(din_a),
        .dout_a(dout_a),
        .we_b(),
        .addr_b(addr_b),
        .din_b(),
        .dout_b(dout_b)
    );
    
endmodule

module vga #(
    parameter PIXEL_BITS    = 4,
    parameter CLK_DIV       = 2,
    parameter H_COUNT_MAX   = 800,
    parameter V_COUNT_MAX   = 525,
    parameter H_BITS        = $clog2(H_COUNT_MAX),
    parameter V_BITS        = $clog2(V_COUNT_MAX)

) (
    input  logic                  clk, 
    input  logic                  rst,

    output logic [PIXEL_BITS-1:0] vga_r,
    output logic [PIXEL_BITS-1:0] vga_g,
    output logic [PIXEL_BITS-1:0] vga_b,
    
    output logic                  h_sync,
    output logic                  v_sync,
    output logic [H_BITS-1:0]     vga_x,
    output logic [V_BITS-1:0]     vga_y,
    output logic                  vga_active
);

    // Clock divider (25MHz enable logic)
    localparam CLK_DIV_BITS = $clog2(CLK_DIV);

    logic                       vga_en; // 25 MHz enable
    logic [CLK_DIV_BITS-1:0]    clk_div_count;

    always_ff @(posedge clk) begin
        if (rst) begin
            vga_en          <= 0;
            clk_div_count   <= 0;
        end
        else begin
            if (clk_div_count == CLK_DIV - 1) begin
                vga_en          <= 1;
                clk_div_count   <= 0;
            end
            else begin
                vga_en          <= 0;
                clk_div_count   <= clk_div_count + 1;
            end
        end
    end

    // Horizontal and Vertical Counter
    logic [H_BITS-1:0]  h_count;
    logic [V_BITS-1:0]  v_count;

    always_ff @(posedge clk) begin
        if (rst) begin
            h_count <= 0;
            v_count <= 0;
        end
        else if (vga_en) begin
            // Horizontal Counter
            if (h_count == H_COUNT_MAX - 1) begin
                h_count <= 0;

                // Vertical Counter
                if (v_count == V_COUNT_MAX - 1) begin
                    v_count <= 0;
                end
                else begin
                    v_count <= v_count + 1;
                end
            end
            else begin
                h_count <= h_count + 1;
            end
        end
    end

    // H-Sync and V-Sync signals
    assign h_sync = (h_count < 96) ? 0 : 1; // active low
    assign v_sync = (v_count < 2) ? 0 : 1;  // active low

    // RGB colors
    assign vga_active = (h_count < 784 && h_count > 143) && (v_count < 515 && v_count > 34) ? 1 : 0;

    assign vga_r = vga_active ? {PIXEL_BITS{1'b1}} : 0;
    assign vga_g = vga_active ? {PIXEL_BITS{1'b1}} : 0;
    assign vga_b = vga_active ? {PIXEL_BITS{1'b1}} : 0;

    // X and Y coordinates
    assign vga_x = vga_active ? (h_count - 144) : 0;
    assign vga_y = vga_active ? (v_count - 35) : 0;

endmodule

module dp_ram_sync_read #(
    parameter DATA_WIDTH = 8,
    parameter MEM_DEPTH  = 1024,
    parameter ADDR_WIDTH = $clog2(MEM_DEPTH)  // 2^10 = 1024 entries
) (
    input  logic                    clk,

    // Port A
    input  logic                    we_a,
    input  logic [ADDR_WIDTH-1:0]   addr_a,
    input  logic [DATA_WIDTH-1:0]   din_a,
    output logic [DATA_WIDTH-1:0]   dout_a,

    // Port B
    input  logic                    we_b,
    input  logic [ADDR_WIDTH-1:0]   addr_b,
    input  logic [DATA_WIDTH-1:0]   din_b,
    output logic [DATA_WIDTH-1:0]   dout_b
);

    logic [DATA_WIDTH-1:0] mem [0:MEM_DEPTH-1];

    always_ff @(posedge clk) begin
        if (we_a) begin
            mem[addr_a] <= din_a;
        end
        dout_a <= mem[addr_a];
    end

    always_ff @(posedge clk) begin
        if (we_b) begin
            mem[addr_b] <= din_b;
        end
        dout_b <= mem[addr_b];
    end

endmodule

module uart_wrapper #(
    parameter CLK_BITS     = 8, // bits for adjustable BAUD rate, min BAUD = F_CLK / (2^CLK_BITS)
    parameter DATA_WIDTH   = 8,
    parameter PARITY_BITS  = 0,
    parameter STOP_BITS    = 1
) (
    input  logic                    clk,
    input  logic                    rst,

    input  logic   [CLK_BITS-1:0]   clk_per_bit,

    input  logic   [DATA_WIDTH-1:0] TX_dataIn,
    input  logic                    TX_en,

    input  logic                    RX_dataIn,

    output logic                    TX_out,
    output logic                    TX_done,
    output logic                    TX_busy,

    output logic   [DATA_WIDTH-1:0] RX_dataOut,
    output logic                    RX_done,
    output logic                    RX_parityError
);
    // UART Transmitter Module
    UART_TX #(
        .CLK_BITS(CLK_BITS),
        .DATA_WIDTH(DATA_WIDTH),
        .PARITY_BITS(PARITY_BITS),
        .STOP_BITS(STOP_BITS)
        ) 
        UART_TX1 ( 
        .clk(clk),
        .rst(rst),

        .clk_per_bit(clk_per_bit),
        .dataIn(TX_dataIn),
        .TXen(TX_en),

        .TXout(TX_out),
        .TXdone(TX_done),
        .busy(TX_busy)
    );

    // UART Receiver Module
    UART_RX #(
        .CLK_BITS(CLK_BITS),
        .DATA_WIDTH(DATA_WIDTH),
        .PARITY_BITS(PARITY_BITS),
        .STOP_BITS(STOP_BITS)
        )
        UART_RX1 (
        .clk(clk),
        .rst(rst),

        .clk_per_bit(clk_per_bit),
        .dataIn(RX_dataIn),

        .RXout(RX_dataOut),
        .RXdone(RX_done),
        .parityError(RX_parityError)
    );
endmodule

module UART_RX #(
    parameter CLK_BITS = 8,   // bits for adjustable BAUD rate, min BAUD = F_CLK / (2^CLK_BITS)
    parameter DATA_WIDTH = 8,
    parameter STOP_BITS = 2,  // either 1 or 2 stop bits
    parameter PARITY_BITS = 1,
    parameter PACKET_SIZE = DATA_WIDTH + STOP_BITS + PARITY_BITS + 1
    // Total Packet Size = DATA_WIDTH + STOP_BITS + 1 Start Bit + 1 Parity Bit
) ( 
    input  logic                                clk,
    input  logic                                rst,

    input  logic    [CLK_BITS - 1 : 0]          clk_per_bit,
    input  logic                                dataIn,

    output logic    [DATA_WIDTH - 1 : 0]         RXout,
    output logic                                RXdone,
    output logic                                parityError
);

    localparam indexBits = $clog2(PACKET_SIZE);

    logic   [indexBits - 1 : 0]     index;
    logic   [CLK_BITS - 1 : 0]      clkCount;

    logic                           regInMeta;
    logic                           regIn;
    logic                           parity;

    logic    [DATA_WIDTH - 1 : 0]    dataOut;
    logic                           dataDone;

    // Remove Problems due to Metastability
    always_ff @(posedge clk) begin
        regInMeta <= dataIn;
        regIn <= regInMeta;
    end



    typedef enum logic [1:0] {
        IDLE,
        START,
        RECEIVE,
        DONE
    } 
    state_t;

    state_t state;

    always_ff @(posedge clk) begin
        if (rst) begin
            dataOut <= 0;
            state <= IDLE;
            index <= 1'b0;
            clkCount <= 0;
            dataDone <= 0;
        end
        else begin
            case (state)
                IDLE: begin
                    clkCount <= 0;
                    index <= 0;
                    dataOut <= 0;
                    dataDone <= 0;

                    if (regIn == 1'b0) begin    // Start Condition
                        state <= START;
                    end
                    else begin
                        state <= IDLE;
                    end
                end

                START: begin
                    if (clkCount == ((clk_per_bit - 1) >> 1)) begin
                        clkCount <= 0;
                        state <= RECEIVE;
                    end
                    else begin
                        clkCount <= clkCount + 1;
                        state <= START;
                    end

                end

                RECEIVE: begin

                    if (clkCount < clk_per_bit - 1) begin
                        clkCount <= clkCount + 1;
                        state <= RECEIVE;
                    end

                    else begin
                        clkCount <= 0;
                        if (index < DATA_WIDTH) begin
                            dataOut[index] <= regIn;
                            index <= index + 1;
                            state <= RECEIVE;
                        end
                        else if (index == DATA_WIDTH && PARITY_BITS > 0) begin
                            parity <= regIn;
                            state <= DONE;
                        end
                        else begin
                            state <= DONE;
                        end
                    end
                end

                DONE: begin
                    if (clkCount < clk_per_bit - 1) begin
                        clkCount <= clkCount + 1;
                        state <= DONE;
                    end
                    else begin
                        clkCount <= 0;
                        state <= IDLE;
                        dataDone <= 1'b1;
                        index <= 0;
                        RXout <= dataOut;
                    end
                end

                default: begin
                    state <= IDLE;
                end
                
            endcase
        end 
    end

    always_comb begin
        RXdone = dataDone;
        if (PARITY_BITS > 0) begin
            parityError = (^RXout) ^ parity;
        end
        else begin
            parityError = 0;
        end
    end
endmodule

module UART_TX #(
    parameter CLK_BITS = 8,         // bits for adjustable BAUD rate, min BAUD = F_CLK / (2^CLK_BITS)
    parameter DATA_WIDTH = 8,
    parameter STOP_BITS = 1,        // either 1 or 2 stop bits
    parameter PARITY_BITS = 1,      // can be set to 0
    parameter PACKET_SIZE = DATA_WIDTH + STOP_BITS + PARITY_BITS + 1 
    // Total Packet Size = DATA_WIDTH + STOP_BITS + 1 Start Bit + 1 Parity Bit
) ( 
    input  logic                                clk,
    input  logic                                rst,

    input  logic      [CLK_BITS - 1 : 0]        clk_per_bit,
    input  logic      [DATA_WIDTH - 1 : 0]      dataIn,
    input  logic                                TXen,

    output logic                                TXout,
    output logic                                TXdone,
    output logic                                busy
);

    localparam indexBits = $clog2(PACKET_SIZE);

    logic   [PACKET_SIZE - 1 : 0]       packet;
    logic                               parityBit;
    logic   [indexBits - 1 : 0]         index;
    logic   [CLK_BITS - 1 : 0]          clkCount;

    typedef enum logic [1:0] {
        IDLE,
        TRANSMIT,
        DONE
    } 
    state_t;

    state_t state;

    always_comb begin
        parityBit = ^dataIn;    // 0 for even number of 1's, 1 for odd number of 1's
    end

    always_ff @(posedge clk) begin
        if (rst) begin
            TXout       <= 1'b1;
            state       <= IDLE;
            busy        <= 1'b0;
            index       <= 1'b0;
            clkCount    <= 0;
            TXdone      <= 0;
        end
        else begin
            case (state)
                IDLE: begin
                    TXout       <= 1'b1;
                    index       <= 1'b0;
                    clkCount    <= 0;
                    TXdone      <= 0;

                    if (TXen) begin
                        if (PARITY_BITS > 0) begin
                            packet <= {{STOP_BITS{1'b1}}, parityBit, dataIn, 1'b0};
                        end 
                        else begin
                            packet <= {{STOP_BITS{1'b1}}, dataIn, 1'b0};
                        end
                        //                ^                         ^
                        //                |                         |
                        //              Stop                      Start
                        busy <= 1'b1;
                        state <= TRANSMIT;
                    end
                    else begin
                        state <= IDLE;
                    end
                end

                TRANSMIT: begin
                    TXout <= packet[index];

                    if (clkCount < clk_per_bit - 1) begin
                        clkCount <= clkCount + 1;
                        state <= TRANSMIT;
                    end

                    else begin
                        clkCount <= 0;
                        if (index == PACKET_SIZE - 1) begin
                            state <= DONE;
                        end
                        else begin
                            index <= index + 1;
                            state <= TRANSMIT;
                        end
                    end
                end

                DONE: begin
                    state       <= IDLE;
                    busy        <= 1'b0;
                    TXdone      <= 1'b1;
                    index       <= 1'b0;
                    clkCount    <= 0;
                end

                default: begin
                    state <= IDLE;
                end
            endcase
        end 
    end
endmodule

VGA/testbench/vga_tb.sv
module tb_vga;

    // Parameters
    localparam PIXEL_BITS  = 4;
    localparam CLK_DIV     = 2;
    localparam H_COUNT_MAX = 800;
    localparam V_COUNT_MAX = 525;
    localparam H_BITS      = $clog2(H_COUNT_MAX);
    localparam V_BITS      = $clog2(V_COUNT_MAX);

    // Clock and reset
    logic clk;
    logic rst;

    // VGA signals
    logic [PIXEL_BITS-1:0] vga_r;
    logic [PIXEL_BITS-1:0] vga_g;
    logic [PIXEL_BITS-1:0] vga_b;
    logic h_sync;
    logic v_sync;
    logic vga_active;
    logic [H_BITS-1:0] vga_x;
    logic [V_BITS-1:0] vga_y;

    // Instantiate VGA module
    vga #(
        .PIXEL_BITS(PIXEL_BITS),
        .CLK_DIV(CLK_DIV),
        .H_COUNT_MAX(H_COUNT_MAX),
        .V_COUNT_MAX(V_COUNT_MAX)
    ) dut (
        .clk(clk),
        .rst(rst),
        .vga_r(vga_r),
        .vga_g(vga_g),
        .vga_b(vga_b),
        .h_sync(h_sync),
        .v_sync(v_sync),
        .vga_x(vga_x),
        .vga_y(vga_y),
        .vga_active(vga_active)
    );

    // Clock generation: 50 MHz
    initial clk = 0;
    always #10 clk = ~clk; // 50MHz -> 20ns period

    // Reset sequence
    initial begin
        rst = 1;
        #100;
        rst = 0;
        #10000
        $finish();
    end

    // Optional waveform dump
    initial begin
        $dumpfile("tb_vga.vcd");
        $dumpvars(0, tb_vga);
    end


endmodule

VGA/sim/tb_vga.vcd
$version Generated by VerilatedVcd $end
$timescale 1ps $end
 $scope module TOP $end
  $scope module tb_vga $end
   $var wire 32 / PIXEL_BITS [31:0] $end
   $var wire 32 0 CLK_DIV [31:0] $end
   $var wire 32 1 H_COUNT_MAX [31:0] $end
   $var wire 32 2 V_COUNT_MAX [31:0] $end
   $var wire 32 3 H_BITS [31:0] $end
   $var wire 32 3 V_BITS [31:0] $end
   $var wire 1 - clk $end
   $var wire 1 . rst $end
   $var wire 4 # vga_r [3:0] $end
   $var wire 4 # vga_g [3:0] $end
   $var wire 4 # vga_b [3:0] $end
   $var wire 1 $ h_sync $end
   $var wire 1 % v_sync $end
   $var wire 1 & vga_active $end
   $var wire 10 ' vga_x [9:0] $end
   $var wire 10 ( vga_y [9:0] $end
   $scope module dut $end
    $var wire 32 / PIXEL_BITS [31:0] $end
    $var wire 32 0 CLK_DIV [31:0] $end
    $var wire 32 1 H_COUNT_MAX [31:0] $end
    $var wire 32 2 V_COUNT_MAX [31:0] $end
    $var wire 32 3 H_BITS [31:0] $end
    $var wire 32 3 V_BITS [31:0] $end
    $var wire 1 - clk $end
    $var wire 1 . rst $end
    $var wire 4 # vga_r [3:0] $end
    $var wire 4 # vga_g [3:0] $end
    $var wire 4 # vga_b [3:0] $end
    $var wire 1 $ h_sync $end
    $var wire 1 % v_sync $end
    $var wire 10 ' vga_x [9:0] $end
    $var wire 10 ( vga_y [9:0] $end
    $var wire 1 & vga_active $end
    $var wire 32 4 CLK_DIV_BITS [31:0] $end
    $var wire 1 ) vga_en $end
    $var wire 1 * clk_div_count [0:0] $end
    $var wire 10 + h_count [9:0] $end
    $var wire 10 , v_count [9:0] $end
   $upscope $end
  $upscope $end
 $upscope $end
$enddefinitions $end


#0
b0000 #
0$
0%
0&
b0000000000 '
b0000000000 (
0)
0*
b0000000000 +
b0000000000 ,
0-
1.
b00000000000000000000000000000100 /
b00000000000000000000000000000010 0
b00000000000000000000001100100000 1
b00000000000000000000001000001101 2
b00000000000000000000000000001010 3
b00000000000000000000000000000001 4
#10
1-
#20
0-
#30
1-
#40
0-
#50
1-
#60
0-
#70
1-
#80
0-
#90
1-
#100
0-
0.
#110
1*
1-
#120
0-
#130
1)
0*
1-
#140
0-
#150
0)
1*
b0000000001 +
1-
#160
0-
#170
1)
0*
1-
#180
0-
#190
0)
1*
b0000000010 +
1-
#200
0-
#210
1)
0*
1-
#220
0-
#230
0)
1*
b0000000011 +
1-
#240
0-
#250
1)
0*
1-
#260
0-
#270
0)
1*
b0000000100 +
1-
#280
0-
#290
1)
0*
1-
#300
0-
#310
0)
1*
b0000000101 +
1-
#320
0-
#330
1)
0*
1-
#340
0-
#350
0)
1*
b0000000110 +
1-
#360
0-
#370
1)
0*
1-
#380
0-
#390
0)
1*
b0000000111 +
1-
#400
0-
#410
1)
0*
1-
#420
0-
#430
0)
1*
b0000001000 +
1-
#440
0-
#450
1)
0*
1-
#460
0-
#470
0)
1*
b0000001001 +
1-
#480
0-
#490
1)
0*
1-
#500
0-
#510
0)
1*
b0000001010 +
1-
#520
0-
#530
1)
0*
1-
#540
0-
#550
0)
1*
b0000001011 +
1-
#560
0-
#570
1)
0*
1-
#580
0-
#590
0)
1*
b0000001100 +
1-
#600
0-
#610
1)
0*
1-
#620
0-
#630
0)
1*
b0000001101 +
1-
#640
0-
#650
1)
0*
1-
#660
0-
#670
0)
1*
b0000001110 +
1-
#680
0-
#690
1)
0*
1-
#700
0-
#710
0)
1*
b0000001111 +
1-
#720
0-
#730
1)
0*
1-
#740
0-
#750
0)
1*
b0000010000 +
1-
#760
0-
#770
1)
0*
1-
#780
0-
#790
0)
1*
b0000010001 +
1-
#800
0-
#810
1)
0*
1-
#820
0-
#830
0)
1*
b0000010010 +
1-
#840
0-
#850
1)
0*
1-
#860
0-
#870
0)
1*
b0000010011 +
1-
#880
0-
#890
1)
0*
1-
#900
0-
#910
0)
1*
b0000010100 +
1-
#920
0-
#930
1)
0*
1-
#940
0-
#950
0)
1*
b0000010101 +
1-
#960
0-
#970
1)
0*
1-
#980
0-
#990
0)
1*
b0000010110 +
1-
#1000
0-
#1010
1)
0*
1-
#1020
0-
#1030
0)
1*
b0000010111 +
1-
#1040
0-
#1050
1)
0*
1-
#1060
0-
#1070
0)
1*
b0000011000 +
1-
#1080
0-
#1090
1)
0*
1-
#1100
0-
#1110
0)
1*
b0000011001 +
1-
#1120
0-
#1130
1)
0*
1-
#1140
0-
#1150
0)
1*
b0000011010 +
1-
#1160
0-
#1170
1)
0*
1-
#1180
0-
#1190
0)
1*
b0000011011 +
1-
#1200
0-
#1210
1)
0*
1-
#1220
0-
#1230
0)
1*
b0000011100 +
1-
#1240
0-
#1250
1)
0*
1-
#1260
0-
#1270
0)
1*
b0000011101 +
1-
#1280
0-
#1290
1)
0*
1-
#1300
0-
#1310
0)
1*
b0000011110 +
1-
#1320
0-
#1330
1)
0*
1-
#1340
0-
#1350
0)
1*
b0000011111 +
1-
#1360
0-
#1370
1)
0*
1-
#1380
0-
#1390
0)
1*
b0000100000 +
1-
#1400
0-
#1410
1)
0*
1-
#1420
0-
#1430
0)
1*
b0000100001 +
1-
#1440
0-
#1450
1)
0*
1-
#1460
0-
#1470
0)
1*
b0000100010 +
1-
#1480
0-
#1490
1)
0*
1-
#1500
0-
#1510
0)
1*
b0000100011 +
1-
#1520
0-
#1530
1)
0*
1-
#1540
0-
#1550
0)
1*
b0000100100 +
1-
#1560
0-
#1570
1)
0*
1-
#1580
0-
#1590
0)
1*
b0000100101 +
1-
#1600
0-
#1610
1)
0*
1-
#1620
0-
#1630
0)
1*
b0000100110 +
1-
#1640
0-
#1650
1)
0*
1-
#1660
0-
#1670
0)
1*
b0000100111 +
1-
#1680
0-
#1690
1)
0*
1-
#1700
0-
#1710
0)
1*
b0000101000 +
1-
#1720
0-
#1730
1)
0*
1-
#1740
0-
#1750
0)
1*
b0000101001 +
1-
#1760
0-
#1770
1)
0*
1-
#1780
0-
#1790
0)
1*
b0000101010 +
1-
#1800
0-
#1810
1)
0*
1-
#1820
0-
#1830
0)
1*
b0000101011 +
1-
#1840
0-
#1850
1)
0*
1-
#1860
0-
#1870
0)
1*
b0000101100 +
1-
#1880
0-
#1890
1)
0*
1-
#1900
0-
#1910
0)
1*
b0000101101 +
1-
#1920
0-
#1930
1)
0*
1-
#1940
0-
#1950
0)
1*
b0000101110 +
1-
#1960
0-
#1970
1)
0*
1-
#1980
0-
#1990
0)
1*
b0000101111 +
1-
#2000
0-
#2010
1)
0*
1-
#2020
0-
#2030
0)
1*
b0000110000 +
1-
#2040
0-
#2050
1)
0*
1-
#2060
0-
#2070
0)
1*
b0000110001 +
1-
#2080
0-
#2090
1)
0*
1-
#2100
0-
#2110
0)
1*
b0000110010 +
1-
#2120
0-
#2130
1)
0*
1-
#2140
0-
#2150
0)
1*
b0000110011 +
1-
#2160
0-
#2170
1)
0*
1-
#2180
0-
#2190
0)
1*
b0000110100 +
1-
#2200
0-
#2210
1)
0*
1-
#2220
0-
#2230
0)
1*
b0000110101 +
1-
#2240
0-
#2250
1)
0*
1-
#2260
0-
#2270
0)
1*
b0000110110 +
1-
#2280
0-
#2290
1)
0*
1-
#2300
0-
#2310
0)
1*
b0000110111 +
1-
#2320
0-
#2330
1)
0*
1-
#2340
0-
#2350
0)
1*
b0000111000 +
1-
#2360
0-
#2370
1)
0*
1-
#2380
0-
#2390
0)
1*
b0000111001 +
1-
#2400
0-
#2410
1)
0*
1-
#2420
0-
#2430
0)
1*
b0000111010 +
1-
#2440
0-
#2450
1)
0*
1-
#2460
0-
#2470
0)
1*
b0000111011 +
1-
#2480
0-
#2490
1)
0*
1-
#2500
0-
#2510
0)
1*
b0000111100 +
1-
#2520
0-
#2530
1)
0*
1-
#2540
0-
#2550
0)
1*
b0000111101 +
1-
#2560
0-
#2570
1)
0*
1-
#2580
0-
#2590
0)
1*
b0000111110 +
1-
#2600
0-
#2610
1)
0*
1-
#2620
0-
#2630
0)
1*
b0000111111 +
1-
#2640
0-
#2650
1)
0*
1-
#2660
0-
#2670
0)
1*
b0001000000 +
1-
#2680
0-
#2690
1)
0*
1-
#2700
0-
#2710
0)
1*
b0001000001 +
1-
#2720
0-
#2730
1)
0*
1-
#2740
0-
#2750
0)
1*
b0001000010 +
1-
#2760
0-
#2770
1)
0*
1-
#2780
0-
#2790
0)
1*
b0001000011 +
1-
#2800
0-
#2810
1)
0*
1-
#2820
0-
#2830
0)
1*
b0001000100 +
1-
#2840
0-
#2850
1)
0*
1-
#2860
0-
#2870
0)
1*
b0001000101 +
1-
#2880
0-
#2890
1)
0*
1-
#2900
0-
#2910
0)
1*
b0001000110 +
1-
#2920
0-
#2930
1)
0*
1-
#2940
0-
#2950
0)
1*
b0001000111 +
1-
#2960
0-
#2970
1)
0*
1-
#2980
0-
#2990
0)
1*
b0001001000 +
1-
#3000
0-
#3010
1)
0*
1-
#3020
0-
#3030
0)
1*
b0001001001 +
1-
#3040
0-
#3050
1)
0*
1-
#3060
0-
#3070
0)
1*
b0001001010 +
1-
#3080
0-
#3090
1)
0*
1-
#3100
0-
#3110
0)
1*
b0001001011 +
1-
#3120
0-
#3130
1)
0*
1-
#3140
0-
#3150
0)
1*
b0001001100 +
1-
#3160
0-
#3170
1)
0*
1-
#3180
0-
#3190
0)
1*
b0001001101 +
1-
#3200
0-
#3210
1)
0*
1-
#3220
0-
#3230
0)
1*
b0001001110 +
1-
#3240
0-
#3250
1)
0*
1-
#3260
0-
#3270
0)
1*
b0001001111 +
1-
#3280
0-
#3290
1)
0*
1-
#3300
0-
#3310
0)
1*
b0001010000 +
1-
#3320
0-
#3330
1)
0*
1-
#3340
0-
#3350
0)
1*
b0001010001 +
1-
#3360
0-
#3370
1)
0*
1-
#3380
0-
#3390
0)
1*
b0001010010 +
1-
#3400
0-
#3410
1)
0*
1-
#3420
0-
#3430
0)
1*
b0001010011 +
1-
#3440
0-
#3450
1)
0*
1-
#3460
0-
#3470
0)
1*
b0001010100 +
1-
#3480
0-
#3490
1)
0*
1-
#3500
0-
#3510
0)
1*
b0001010101 +
1-
#3520
0-
#3530
1)
0*
1-
#3540
0-
#3550
0)
1*
b0001010110 +
1-
#3560
0-
#3570
1)
0*
1-
#3580
0-
#3590
0)
1*
b0001010111 +
1-
#3600
0-
#3610
1)
0*
1-
#3620
0-
#3630
0)
1*
b0001011000 +
1-
#3640
0-
